{
    "name": "Example",
    "children": [{
            "name": "Robert Baratheon",
            "children": [{


                    "name": "Bob Baratheon",
                    "children": [{
                            "name": "Bobette Baratheon",
                            "children": [{
                                    "name": "Bobby Baratheon",
                                    "children": [{
                                            "name": "Bobette Baratheon",
                                            "children": [{
                                                "name": "Bobert Baratheon"
                                            }]
                                        },
                                        {
                                            "name": "Bobby Baratheon",
                                            "children": [{
                                                    "name": "Bobette Baratheon"
                                                },
                                                {
                                                    "name": "Bobby Baratheon"
                                                },
                                                {
                                                    "name": "Bobert Baratheon"
                                                }
                                            ]
                                        },
                                        {
                                            "name": "Bobert Baratheon",
                                            "children": [{
                                                    "name": "Bobette Baratheon"
                                                },

                                                {
                                                    "name": "Bobert Baratheon"
                                                }
                                            ]
                                        }
                                    ]
                                },
                                {
                                    "name": "Bobert Baratheon",
                                    "children": [{
                                            "name": "Bobette Baratheon",
                                            "children": [{
                                                "name": "Bobette Baratheon"
                                            }]
                                        },
                                        {
                                            "name": "Bobby Baratheon",
                                            "children": [{
                                                    "name": "Bobette Baratheon"
                                                },
                                                {
                                                    "name": "Bobby Baratheon"
                                                },
                                                {
                                                    "name": "Bobert Baratheon"
                                                }
                                            ]
                                        },
                                        {
                                            "name": "Bobert Baratheon",
                                            "children": [{
                                                    "name": "Bobette Baratheon"
                                                },
                                                {
                                                    "name": "Bobby Baratheon"
                                                },
                                                {
                                                    "name": "Bobert Baratheon"
                                                }
                                            ]
                                        }
                                    ]
                                }
                            ]
                        },
                        {
                            "name": "Bobby Baratheon",
                            "children": [{
                                    "name": "Bobette Baratheon",
                                    "children": [{
                                            "name": "Bobette Baratheon",
                                            "children": [{
                                                    "name": "Bobette Baratheon"
                                                },
                                                {
                                                    "name": "Bobby Baratheon"
                                                },
                                                {
                                                    "name": "Bobert Baratheon"
                                                }
                                            ]
                                        },
                                        {
                                            "name": "Bobby Baratheon",
                                            "children": [{
                                                    "name": "Bobette Baratheon"
                                                },
                                                {
                                                    "name": "Bobby Baratheon"
                                                },
                                                {
                                                    "name": "Bobert Baratheon"
                                                }
                                            ]
                                        },
                                        {
                                            "name": "Bobert Baratheon",
                                            "children": [{
                                                    "name": "Bobette Baratheon"
                                                },
                                                {
                                                    "name": "Bobby Baratheon"
                                                },
                                                {
                                                    "name": "Bobert Baratheon"
                                                }
                                            ]
                                        }
                                    ]
                                },
                                {
                                    "name": "Bobby Baratheon",
                                    "children": [

                                        {
                                            "name": "Bobby Baratheon",
                                            "children": [{
                                                    "name": "Bobette Baratheon"
                                                },
                                                {
                                                    "name": "Bobby Baratheon"
                                                },
                                                {
                                                    "name": "Bobert Baratheon"
                                                }
                                            ]
                                        },
                                        {
                                            "name": "Bobert Baratheon",
                                            "children": [{
                                                    "name": "Bobette Baratheon"
                                                },
                                                {
                                                    "name": "Bobby Baratheon"
                                                },
                                                {
                                                    "name": "Bobert Baratheon"
                                                }
                                            ]
                                        }
                                    ]
                                },
                                {
                                    "name": "Bobert Baratheon",
                                    "children": [{
                                            "name": "Bobette Baratheon",
                                            "children": [{
                                                    "name": "Bobette Baratheon"
                                                },
                                                {
                                                    "name": "Bobby Baratheon"
                                                },
                                                {
                                                    "name": "Bobert Baratheon"
                                                }
                                            ]
                                        },
                                        {
                                            "name": "Bobby Baratheon",
                                            "children": [{
                                                    "name": "Bobette Baratheon"
                                                },
                                                {
                                                    "name": "Bobby Baratheon"
                                                },
                                                {
                                                    "name": "Bobert Baratheon"
                                                }
                                            ]
                                        },
                                        {
                                            "name": "Bobert Baratheon",
                                            "children": [{
                                                    "name": "Bobette Baratheon"
                                                },
                                                {
                                                    "name": "Bobby Baratheon"
                                                },
                                                {
                                                    "name": "Bobert Baratheon"
                                                }
                                            ]
                                        }
                                    ]
                                }
                            ]
                        },
                        {
                            "name": "Bobert Baratheon",
                            "children": [{
                                    "name": "Bobette Baratheon",
                                    "children": [{
                                            "name": "Bobette Baratheon"
                                        },
                                        {
                                            "name": "Bobby Baratheon"
                                        },
                                        {
                                            "name": "Bobert Baratheon"
                                        }
                                    ]
                                },
                                {
                                    "name": "Bobby Baratheon",
                                    "children": [{
                                            "name": "Bobette Baratheon"
                                        },
                                        {
                                            "name": "Bobby Baratheon"
                                        },
                                        {
                                            "name": "Bobert Baratheon"
                                        }
                                    ]
                                },
                                {
                                    "name": "Bobert Baratheon",
                                    "children": [{
                                            "name": "Bobette Baratheon"
                                        },
                                        {
                                            "name": "Bobby Baratheon"
                                        },
                                        {
                                            "name": "Bobert Baratheon"
                                        }
                                    ]
                                }
                            ]
                        }
                    ]
                },
                {
                    "name": "Bob Baratheon",
                    "children": [{
                            "name": "Bobette Baratheon",
                            "children": [{
                                    "name": "Bobette Baratheon",
                                    "children": [{
                                            "name": "Bobette Baratheon",
                                            "children": [{
                                                    "name": "Bobette Baratheon"
                                                },
                                                {
                                                    "name": "Bobby Baratheon"
                                                },
                                                {
                                                    "name": "Bobert Baratheon"
                                                }
                                            ]
                                        },
                                        {
                                            "name": "Bobby Baratheon",
                                            "children": [{
                                                    "name": "Bobette Baratheon"
                                                },
                                                {
                                                    "name": "Bobby Baratheon"
                                                },
                                                {
                                                    "name": "Bobert Baratheon"
                                                }
                                            ]
                                        },
                                        {
                                            "name": "Bobert Baratheon",
                                            "children": [{
                                                    "name": "Bobette Baratheon"
                                                },
                                                {
                                                    "name": "Bobby Baratheon"
                                                },
                                                {
                                                    "name": "Bobert Baratheon"
                                                }
                                            ]
                                        }
                                    ]
                                },
                                {
                                    "name": "Bobby Baratheon",
                                    "children": [{
                                            "name": "Bobette Baratheon",
                                            "children": [{
                                                    "name": "Bobette Baratheon"
                                                },
                                                {
                                                    "name": "Bobby Baratheon"
                                                },
                                                {
                                                    "name": "Bobert Baratheon"
                                                }
                                            ]
                                        },
                                        {
                                            "name": "Bobby Baratheon",
                                            "children": [{
                                                    "name": "Bobette Baratheon"
                                                },
                                                {
                                                    "name": "Bobby Baratheon"
                                                },
                                                {
                                                    "name": "Bobert Baratheon"
                                                }
                                            ]
                                        },
                                        {
                                            "name": "Bobert Baratheon",
                                            "children": [{
                                                    "name": "Bobette Baratheon"
                                                },
                                                {
                                                    "name": "Bobby Baratheon"
                                                },
                                                {
                                                    "name": "Bobert Baratheon"
                                                }
                                            ]
                                        }
                                    ]
                                },
                                {
                                    "name": "Bobert Baratheon",
                                    "children": [{
                                            "name": "Bobette Baratheon",
                                            "children": [{
                                                    "name": "Bobette Baratheon"
                                                },
                                                {
                                                    "name": "Bobby Baratheon"
                                                },
                                                {
                                                    "name": "Bobert Baratheon"
                                                }
                                            ]
                                        },
                                        {
                                            "name": "Bobby Baratheon",
                                            "children": [{
                                                    "name": "Bobette Baratheon"
                                                },
                                                {
                                                    "name": "Bobby Baratheon"
                                                },
                                                {
                                                    "name": "Bobert Baratheon"
                                                }
                                            ]
                                        },
                                        {
                                            "name": "Bobert Baratheon",
                                            "children": [{
                                                    "name": "Bobette Baratheon"
                                                },
                                                {
                                                    "name": "Bobby Baratheon"
                                                },
                                                {
                                                    "name": "Bobert Baratheon"
                                                }
                                            ]
                                        }
                                    ]
                                }
                            ]
                        },
                        {
                            "name": "Bobby Baratheon",
                            "children": [{
                                    "name": "Bobette Baratheon",
                                    "children": [{
                                            "name": "Bobette Baratheon",
                                            "children": [{
                                                    "name": "Bobette Baratheon"
                                                },
                                                {
                                                    "name": "Bobby Baratheon"
                                                },
                                                {
                                                    "name": "Bobert Baratheon"
                                                }
                                            ]
                                        },
                                        {
                                            "name": "Bobby Baratheon",
                                            "children": [{
                                                    "name": "Bobette Baratheon"
                                                },
                                                {
                                                    "name": "Bobby Baratheon"
                                                },
                                                {
                                                    "name": "Bobert Baratheon"
                                                }
                                            ]
                                        },
                                        {
                                            "name": "Bobert Baratheon",
                                            "children": [{
                                                    "name": "Bobette Baratheon"
                                                },
                                                {
                                                    "name": "Bobby Baratheon"
                                                },
                                                {
                                                    "name": "Bobert Baratheon"
                                                }
                                            ]
                                        }
                                    ]
                                },
                                {
                                    "name": "Bobby Baratheon",
                                    "children": [{
                                            "name": "Bobette Baratheon",
                                            "children": [{
                                                    "name": "Bobette Baratheon"
                                                },
                                                {
                                                    "name": "Bobby Baratheon"
                                                },
                                                {
                                                    "name": "Bobert Baratheon"
                                                }
                                            ]
                                        },
                                        {
                                            "name": "Bobby Baratheon",
                                            "children": [{
                                                    "name": "Bobette Baratheon"
                                                },
                                                {
                                                    "name": "Bobby Baratheon"
                                                },
                                                {
                                                    "name": "Bobert Baratheon"
                                                }
                                            ]
                                        },
                                        {
                                            "name": "Bobert Baratheon",
                                            "children": [{
                                                    "name": "Bobette Baratheon"
                                                },
                                                {
                                                    "name": "Bobby Baratheon"
                                                },
                                                {
                                                    "name": "Bobert Baratheon"
                                                }
                                            ]
                                        }
                                    ]
                                },
                                {
                                    "name": "Bobert Baratheon",
                                    "children": [{
                                            "name": "Bobette Baratheon",
                                            "children": [{
                                                    "name": "Bobette Baratheon"
                                                },
                                                {
                                                    "name": "Bobby Baratheon"
                                                },
                                                {
                                                    "name": "Bobert Baratheon"
                                                }
                                            ]
                                        },
                                        {
                                            "name": "Bobby Baratheon",
                                            "children": [{
                                                    "name": "Bobette Baratheon"
                                                },
                                                {
                                                    "name": "Bobby Baratheon"
                                                },
                                                {
                                                    "name": "Bobert Baratheon"
                                                }
                                            ]
                                        },
                                        {
                                            "name": "Bobert Baratheon",
                                            "children": [{
                                                    "name": "Bobette Baratheon"
                                                },
                                                {
                                                    "name": "Bobby Baratheon"
                                                },
                                                {
                                                    "name": "Bobert Baratheon"
                                                }
                                            ]
                                        }
                                    ]
                                }
                            ]
                        },
                        {
                            "name": "Bobert Baratheon",
                            "children": [{
                                    "name": "Bobette Baratheon",
                                    "children": [{
                                            "name": "Bobette Baratheon"
                                        },
                                        {
                                            "name": "Bobby Baratheon"
                                        },
                                        {
                                            "name": "Bobert Baratheon"
                                        }
                                    ]
                                },
                                {
                                    "name": "Bobby Baratheon",
                                    "children": [{
                                            "name": "Bobette Baratheon"
                                        },
                                        {
                                            "name": "Bobby Baratheon"
                                        },
                                        {
                                            "name": "Bobert Baratheon"
                                        }
                                    ]
                                },
                                {
                                    "name": "Bobert Baratheon",
                                    "children": [{
                                            "name": "Bobette Baratheon"
                                        },
                                        {
                                            "name": "Bobby Baratheon"
                                        },
                                        {
                                            "name": "Bobert Baratheon"
                                        }
                                    ]
                                }
                            ]
                        }
                    ]
                }
            ]
        },
        {
            "name": "Bobo Baratheon",
            "children": [{
                    "name": "Bob Baratheon",
                    "children": [{
                            "name": "Bobby Baratheon",
                            "children": [{
                                    "name": "Bobette Baratheon",
                                    "children": [{
                                            "name": "Bobette Baratheon"
                                        },
                                        {
                                            "name": "Bobby Baratheon"

                                        },
                                        {
                                            "name": "Bobert Baratheon",
                                            "children": [{
                                                    "name": "Bobette Baratheon"
                                                },
                                                {
                                                    "name": "Bobby Baratheon"
                                                },
                                                {
                                                    "name": "Bobert Baratheon"
                                                }
                                            ]
                                        }
                                    ]
                                },
                                {
                                    "name": "Bobby Baratheon",
                                    "children": [{
                                            "name": "Bobette Baratheon",
                                            "children": [{
                                                    "name": "Bobette Baratheon"
                                                },

                                                {
                                                    "name": "Bobert Baratheon"
                                                }
                                            ]
                                        },
                                        {
                                            "name": "Bobby Baratheon"

                                        },
                                        {
                                            "name": "Bobert Baratheon"

                                        }
                                    ]
                                }

                            ]
                        },
                        {
                            "name": "Bobert Baratheon",
                            "children": [{
                                    "name": "Bobette Baratheon",
                                    "children": [{
                                            "name": "Bobette Baratheon"
                                        },
                                        {
                                            "name": "Bobby Baratheon"
                                        },
                                        {
                                            "name": "Bobert Baratheon"
                                        }
                                    ]
                                },
                                {
                                    "name": "Bobby Baratheon",
                                    "children": [{
                                            "name": "Bobette Baratheon"
                                        },
                                        {
                                            "name": "Bobby Baratheon"
                                        },
                                        {
                                            "name": "Bobert Baratheon"
                                        }
                                    ]
                                },
                                {
                                    "name": "Bobert Baratheon",
                                    "children": [{
                                        "name": "Bobette Baratheon"
                                    }]
                                }
                            ]
                        }
                    ]
                },
                {
                    "name": "Bob Baratheon",
                    "children": [{
                            "name": "Bobette Baratheon",
                            "children": [{
                                    "name": "Bobette Baratheon",
                                    "children": [{
                                            "name": "Bobette Baratheon",
                                            "children": [{
                                                    "name": "Bobette Baratheon"
                                                },
                                                {
                                                    "name": "Bobby Baratheon"
                                                }

                                            ]
                                        },
                                        {
                                            "name": "Bobby Baratheon",
                                            "children": [{
                                                    "name": "Bobette Baratheon"
                                                },
                                                {
                                                    "name": "Bobby Baratheon"
                                                },
                                                {
                                                    "name": "Bobert Baratheon"
                                                }
                                            ]
                                        },
                                        {
                                            "name": "Bobert Baratheon",
                                            "children": [{
                                                    "name": "Bobette Baratheon"
                                                },

                                                {
                                                    "name": "Bobert Baratheon"
                                                }
                                            ]
                                        }
                                    ]
                                },

                                {
                                    "name": "Bobert Baratheon",
                                    "children": [{
                                            "name": "Bobette Baratheon"

                                        },
                                        {
                                            "name": "Bobby Baratheon",
                                            "children": [{
                                                    "name": "Bobette Baratheon"
                                                },

                                                {
                                                    "name": "Bobert Baratheon"
                                                }
                                            ]
                                        },
                                        {
                                            "name": "Bobert Baratheon",
                                            "children": [{
                                                    "name": "Bobette Baratheon"
                                                },

                                                {
                                                    "name": "Bobert Baratheon"
                                                }
                                            ]
                                        }
                                    ]
                                }
                            ]
                        },
                        {
                            "name": "Bobby Baratheon",
                            "children": [{
                                    "name": "Bobette Baratheon",
                                    "children": [{
                                            "name": "Bobette Baratheon",
                                            "children": [{
                                                    "name": "Bobette Baratheon"
                                                },
                                                {
                                                    "name": "Bobby Baratheon"
                                                },
                                                {
                                                    "name": "Bobert Baratheon"
                                                }
                                            ]
                                        },

                                        {
                                            "name": "Bobert Baratheon",
                                            "children": [{
                                                    "name": "Bobette Baratheon"
                                                },
                                                {
                                                    "name": "Bobby Baratheon"
                                                },
                                                {
                                                    "name": "Bobert Baratheon"
                                                }
                                            ]
                                        }
                                    ]
                                },
                                {
                                    "name": "Bobby Baratheon",
                                    "children": [{
                                            "name": "Bobette Baratheon",
                                            "children": [{
                                                    "name": "Bobette Baratheon"
                                                },
                                                {
                                                    "name": "Bobby Baratheon"
                                                },
                                                {
                                                    "name": "Bobert Baratheon"
                                                }
                                            ]
                                        },
                                        {
                                            "name": "Bobby Baratheon",
                                            "children": [{
                                                    "name": "Bobette Baratheon"
                                                },
                                                {
                                                    "name": "Bobby Baratheon"
                                                },
                                                {
                                                    "name": "Bobert Baratheon"
                                                }
                                            ]
                                        },
                                        {
                                            "name": "Bobert Baratheon",
                                            "children": [{
                                                    "name": "Bobette Baratheon"
                                                },
                                                {
                                                    "name": "Bobby Baratheon"
                                                },
                                                {
                                                    "name": "Bobert Baratheon"
                                                }
                                            ]
                                        }
                                    ]
                                },
                                {
                                    "name": "Bobert Baratheon",
                                    "children": [{
                                            "name": "Bobette Baratheon",
                                            "children": [{
                                                    "name": "Bobette Baratheon"
                                                },
                                                {
                                                    "name": "Bobby Baratheon"
                                                },
                                                {
                                                    "name": "Bobert Baratheon"
                                                }
                                            ]
                                        },
                                        {
                                            "name": "Bobby Baratheon",
                                            "children": [{
                                                    "name": "Bobette Baratheon"
                                                },
                                                {
                                                    "name": "Bobby Baratheon"
                                                },
                                                {
                                                    "name": "Bobert Baratheon"
                                                }
                                            ]
                                        },
                                        {
                                            "name": "Bobert Baratheon",
                                            "children": [{
                                                    "name": "Bobette Baratheon"
                                                },
                                                {
                                                    "name": "Bobby Baratheon"
                                                },
                                                {
                                                    "name": "Bobert Baratheon"
                                                }
                                            ]
                                        }
                                    ]
                                }
                            ]
                        },
                        {
                            "name": "Bobert Baratheon"
                        }
                    ]

                }
            ]
        },
        {
            "name": "Bobina Baratheon",
            "children": [{
                    "name": "Bob Baratheon",
                    "children": [{
                            "name": "Bobette Baratheon",
                            "children": [{
                                    "name": "Bobette Baratheon",
                                    "children": [{
                                            "name": "Bobby Baratheon",
                                            "children": [{
                                                    "name": "Bobby Baratheon"
                                                },
                                                {
                                                    "name": "Bobert Baratheon"
                                                }
                                            ]
                                        },
                                        {
                                            "name": "Bobert Baratheon",
                                            "children": [{
                                                    "name": "Bobette Baratheon"
                                                },
                                                {
                                                    "name": "Bobby Baratheon"
                                                },
                                                {
                                                    "name": "Bobert Baratheon"
                                                }
                                            ]
                                        }
                                    ]
                                },
                                {
                                    "name": "Bobby Baratheon",
                                    "children": [{
                                            "name": "Bobette Baratheon",
                                            "children": [{
                                                    "name": "Bobette Baratheon"
                                                },
                                                {
                                                    "name": "Bobby Baratheon"
                                                },
                                                {
                                                    "name": "Bobert Baratheon"
                                                }
                                            ]
                                        },
                                        {
                                            "name": "Bobby Baratheon",
                                            "children": [{
                                                    "name": "Bobette Baratheon"
                                                },
                                                {
                                                    "name": "Bobby Baratheon"
                                                },
                                                {
                                                    "name": "Bobert Baratheon"
                                                }
                                            ]
                                        },
                                        {
                                            "name": "Bobert Baratheon",
                                            "children": [{
                                                    "name": "Bobette Baratheon"
                                                },
                                                {
                                                    "name": "Bobby Baratheon"
                                                },
                                                {
                                                    "name": "Bobert Baratheon"
                                                }
                                            ]
                                        }
                                    ]
                                },
                                {
                                    "name": "Bobert Baratheon",
                                    "children": [{
                                            "name": "Bobette Baratheon",
                                            "children": [{
                                                    "name": "Bobette Baratheon"
                                                },
                                                {
                                                    "name": "Bobby Baratheon"
                                                },
                                                {
                                                    "name": "Bobert Baratheon"
                                                }
                                            ]
                                        },
                                        {
                                            "name": "Bobby Baratheon",
                                            "children": [{
                                                    "name": "Bobette Baratheon"
                                                },
                                                {
                                                    "name": "Bobby Baratheon"
                                                },
                                                {
                                                    "name": "Bobert Baratheon"
                                                }
                                            ]
                                        },
                                        {
                                            "name": "Bobert Baratheon",
                                            "children": [{
                                                    "name": "Bobette Baratheon"
                                                },
                                                {
                                                    "name": "Bobby Baratheon"
                                                },
                                                {
                                                    "name": "Bobert Baratheon"
                                                }
                                            ]
                                        }
                                    ]
                                }
                            ]
                        },
                        {
                            "name": "Bobby Baratheon",
                            "children": [{
                                    "name": "Bobette Baratheon",
                                    "children": [{
                                            "name": "Bobette Baratheon",
                                            "children": [{
                                                    "name": "Bobette Baratheon"
                                                },
                                                {
                                                    "name": "Bobby Baratheon"
                                                },
                                                {
                                                    "name": "Bobert Baratheon"
                                                }
                                            ]
                                        },
                                        {
                                            "name": "Bobby Baratheon",
                                            "children": [{
                                                    "name": "Bobette Baratheon"
                                                },
                                                {
                                                    "name": "Bobby Baratheon"
                                                },
                                                {
                                                    "name": "Bobert Baratheon"
                                                }
                                            ]
                                        },
                                        {
                                            "name": "Bobert Baratheon",
                                            "children": [{
                                                    "name": "Bobette Baratheon"
                                                },
                                                {
                                                    "name": "Bobby Baratheon"
                                                },
                                                {
                                                    "name": "Bobert Baratheon"
                                                }
                                            ]
                                        }
                                    ]
                                },

                                {
                                    "name": "Bobert Baratheon",
                                    "children": [{
                                            "name": "Bobette Baratheon",
                                            "children": [{
                                                    "name": "Bobette Baratheon"
                                                },
                                                {
                                                    "name": "Bobby Baratheon"
                                                },
                                                {
                                                    "name": "Bobert Baratheon"
                                                }
                                            ]
                                        },
                                        {
                                            "name": "Bobby Baratheon",
                                            "children": [{
                                                    "name": "Bobette Baratheon"
                                                },
                                                {
                                                    "name": "Bobby Baratheon"
                                                },
                                                {
                                                    "name": "Bobert Baratheon"
                                                }
                                            ]
                                        },
                                        {
                                            "name": "Bobert Baratheon",
                                            "children": [{
                                                    "name": "Bobette Baratheon"
                                                },
                                                {
                                                    "name": "Bobby Baratheon"
                                                },
                                                {
                                                    "name": "Bobert Baratheon"
                                                }
                                            ]
                                        }
                                    ]
                                }
                            ]
                        }
                    ]
                }


            ]
        }
    ]
}
